Oxomoc-0.1.0.data/scripts/oxomoc_run
oxomoc/__init__.py
oxomoc/_version.py
oxomoc/checkpoint.py
oxomoc/ckpselective.py
oxomoc/harvester.py
Oxomoc-0.1.0.dist-info/LICENSE
Oxomoc-0.1.0.dist-info/METADATA
Oxomoc-0.1.0.dist-info/WHEEL
Oxomoc-0.1.0.dist-info/top_level.txt
Oxomoc-0.1.0.dist-info/RECORD
