Metadata-Version: 2.2
Name: Oxomoc
Version: 0.1.0
Summary: Colav OAI-PMH Harvester
Home-page: https://github.com/colav/Oxomoc
Author: Colav
Author-email: colav@udea.edu.co
License: BSD
License-File: LICENSE
Requires-Dist: xmltodict>=0.13.0
Requires-Dist: pyoai>=2.5.0
Requires-Dist: ratelimit>=2.2.1
Requires-Dist: psutil
Requires-Dist: pymongo>=3.12.0
Requires-Dist: joblib>=1.1.0
Requires-Dist: lxml==4.9.3
Dynamic: author
Dynamic: author-email
Dynamic: description
Dynamic: description-content-type
Dynamic: home-page
Dynamic: license
Dynamic: requires-dist
Dynamic: summary
